{
  "runnerInfo": {
    "name": "Aurelie ZAHM (A7337726)"
  },
  "runs": [
    {
      "event": "Osterley",
      "date": "27/12/2025",
      "position": "86",
      "time": "25:11",
      "ageGrade": "62.01%",
      "isPB": false
    },
    {
      "event": "Richmond Park",
      "date": "25/12/2025",
      "position": "368",
      "time": "29:28",
      "ageGrade": "53.00%",
      "isPB": false
    },
    {
      "event": "Osterley",
      "date": "20/12/2025",
      "position": "117",
      "time": "26:42",
      "ageGrade": "58.49%",
      "isPB": false
    },
    {
      "event": "Old Deer Park",
      "date": "13/12/2025",
      "position": "64",
      "time": "27:16",
      "ageGrade": "57.27%",
      "isPB": false
    },
    {
      "event": "York",
      "date": "06/12/2025",
      "position": "326",
      "time": "28:11",
      "ageGrade": "55.41%",
      "isPB": false
    },
    {
      "event": "Osterley",
      "date": "29/11/2025",
      "position": "99",
      "time": "26:46",
      "ageGrade": "58.34%",
      "isPB": false
    },
    {
      "event": "Hanworth",
      "date": "22/11/2025",
      "position": "35",
      "time": "30:36",
      "ageGrade": "51.03%",
      "isPB": false
    },
    {
      "event": "Osterley",
      "date": "15/11/2025",
      "position": "119",
      "time": "26:54",
      "ageGrade": "58.05%",
      "isPB": false
    },
    {
      "event": "Osterley",
      "date": "25/10/2025",
      "position": "117",
      "time": "26:51",
      "ageGrade": "58.16%",
      "isPB": false
    },
    {
      "event": "Osterley",
      "date": "11/10/2025",
      "position": "105",
      "time": "26:51",
      "ageGrade": "58.16%",
      "isPB": false
    },
    {
      "event": "Old Deer Park",
      "date": "04/10/2025",
      "position": "170",
      "time": "27:13",
      "ageGrade": "57.38%",
      "isPB": false
    },
    {
      "event": "Mile End",
      "date": "20/09/2025",
      "position": "482",
      "time": "34:29",
      "ageGrade": "45.29%",
      "isPB": false
    },
    {
      "event": "Gunnersbury",
      "date": "13/09/2025",
      "position": "409",
      "time": "30:46",
      "ageGrade": "50.76%",
      "isPB": false
    },
    {
      "event": "Osterley",
      "date": "30/08/2025",
      "position": "184",
      "time": "29:05",
      "ageGrade": "53.70%",
      "isPB": false
    },
    {
      "event": "Bushy Park",
      "date": "23/08/2025",
      "position": "926",
      "time": "29:21",
      "ageGrade": "53.21%",
      "isPB": false
    },
    {
      "event": "Osterley",
      "date": "16/08/2025",
      "position": "301",
      "time": "37:32",
      "ageGrade": "41.61%",
      "isPB": false
    },
    {
      "event": "Osterley",
      "date": "02/08/2025",
      "position": "284",
      "time": "34:16",
      "ageGrade": "45.57%",
      "isPB": false
    },
    {
      "event": "Osterley",
      "date": "26/07/2025",
      "position": "316",
      "time": "37:34",
      "ageGrade": "41.57%",
      "isPB": false
    },
    {
      "event": "Old Deer Park",
      "date": "12/07/2025",
      "position": "128",
      "time": "34:28",
      "ageGrade": "45.31%",
      "isPB": false
    },
    {
      "event": "Dreiländergarten",
      "date": "21/06/2025",
      "position": "33",
      "time": "47:06",
      "ageGrade": "33.16%",
      "isPB": false
    },
    {
      "event": "Finsbury Park",
      "date": "14/06/2025",
      "position": "751",
      "time": "36:56",
      "ageGrade": "42.28%",
      "isPB": false
    },
    {
      "event": "Osterley",
      "date": "07/06/2025",
      "position": "223",
      "time": "30:41",
      "ageGrade": "50.90%",
      "isPB": false
    },
    {
      "event": "Old Deer Park",
      "date": "31/05/2025",
      "position": "157",
      "time": "31:11",
      "ageGrade": "50.08%",
      "isPB": false
    },
    {
      "event": "Osterley",
      "date": "24/05/2025",
      "position": "330",
      "time": "36:06",
      "ageGrade": "43.26%",
      "isPB": false
    },
    {
      "event": "Osterley",
      "date": "17/05/2025",
      "position": "357",
      "time": "37:47",
      "ageGrade": "41.33%",
      "isPB": false
    },
    {
      "event": "Old Deer Park",
      "date": "19/04/2025",
      "position": "139",
      "time": "42:31",
      "ageGrade": "36.73%",
      "isPB": false
    },
    {
      "event": "Osterley",
      "date": "12/04/2025",
      "position": "361",
      "time": "43:17",
      "ageGrade": "36.08%",
      "isPB": false
    },
    {
      "event": "Richmond Park",
      "date": "05/04/2025",
      "position": "480",
      "time": "45:47",
      "ageGrade": "34.11%",
      "isPB": false
    },
    {
      "event": "Osterley",
      "date": "29/03/2025",
      "position": "317",
      "time": "45:22",
      "ageGrade": "34.42%",
      "isPB": false
    },
    {
      "event": "Old Deer Park",
      "date": "08/03/2025",
      "position": "168",
      "time": "1:02:42",
      "ageGrade": "24.72%",
      "isPB": false
    }
  ],
  "statistics": {
    "totalRuns": 30,
    "firstRun": "08/03/2025",
    "latestRun": "27/12/2025",
    "bestTime": "25:11",
    "uniqueEvents": 10
  }
}